MANIFEST.in
README.md
requirements.txt
setup.py
hpoo/__init__.py
hpoo/core.py
hpoo.egg-info/PKG-INFO
hpoo.egg-info/SOURCES.txt
hpoo.egg-info/dependency_links.txt
hpoo.egg-info/requires.txt
hpoo.egg-info/top_level.txt