Metadata-Version: 1.1
Name: hpoo
Version: 0.0.3
Summary: HPOO v10 python SDK (non-official)
Home-page: https://github.com/fvillain/hpoopy
Author: Francois Villain
Author-email: francois.villain@gmail.com
License: WTFPL
Platform: UNKNOWN
Classifier: Programming Language :: Python
Classifier: Operating System :: OS Independent
Classifier: Programming Language :: Python :: 3.4
